rodlayout/__init__.py
rodlayout/canvas.py
rodlayout/layer.py
rodlayout/proxy.py
rodlayout/transform.py
rodlayout/version.py
tests/__init__.py
tests/test_create.py
rodlayout-0.1.5.dist-info/LICENSE
rodlayout-0.1.5.dist-info/METADATA
rodlayout-0.1.5.dist-info/WHEEL
rodlayout-0.1.5.dist-info/top_level.txt
rodlayout-0.1.5.dist-info/RECORD
