Metadata-Version: 2.1
Name: rodlayout
Version: 0.1.5
Summary: A python wrapper for the Skill objects in virtuoso
Home-page: UNKNOWN
Author: Niels Buwen
Author-email: dev@niels-buwen.de
License: UNKNOWN
Platform: UNKNOWN
Classifier: Development Status :: 4 - Beta
Classifier: Programming Language :: Python :: 3
Classifier: Programming Language :: Python :: 3.6
Classifier: Programming Language :: Python :: 3.7
Classifier: Programming Language :: Python :: 3.8
Classifier: Intended Audience :: Developers
Classifier: Operating System :: POSIX :: Linux
Classifier: Topic :: Software Development
Classifier: License :: OSI Approved :: GNU Lesser General Public License v3 (LGPLv3)
Requires-Dist: simple-geometry
Requires-Dist: skillbridge
